{"entities": {"base_0": {"id": 0, "recipes": []}, "base_1": {"id": 1, "recipes": []}, "base_2": {"id": 2, "recipes": []}, "base_3": {"id": 3, "recipes": []}, "base_4": {"id": 4, "recipes": []}, "base_5": {"id": 5, "recipes": []}, "a_0": {"id": 6, "recipes": [["base_0", "base_0"]]}, "b_0": {"id": 7, "recipes": [["base_5", "base_3"]]}, "a_1": {"id": 8, "recipes": [["a_0", "base_4"]]}, "b_1": {"id": 9, "recipes": [["b_0", "base_3"]]}, "a_2": {"id": 10, "recipes": [["a_1", "base_1"]]}, "b_2": {"id": 11, "recipes": [["b_1", "base_1"]]}, "a_3": {"id": 12, "recipes": [["a_2", "base_4"]]}, "b_3": {"id": 13, "recipes": [["b_2", "base_5"]]}, "a_4": {"id": 14, "recipes": [["a_3", "base_2"]]}, "b_4": {"id": 15, "recipes": [["b_3", "base_1"]]}, "a_5": {"id": 16, "recipes": [["a_4", "base_2"]]}, "b_5": {"id": 17, "recipes": [["b_4", "base_2"]]}, "a_6": {"id": 18, "recipes": [["a_5", "base_2"]]}, "b_6": {"id": 19, "recipes": [["b_5", "base_1"]]}, "a_7": {"id": 20, "recipes": [["a_6", "base_2"]]}, "b_7": {"id": 21, "recipes": [["b_6", "base_0"]]}, "a_8": {"id": 22, "recipes": [["a_7", "base_4"]]}, "b_8": {"id": 23, "recipes": [["b_7", "base_5"]]}, "a_9": {"id": 24, "recipes": [["a_8", "base_0"]]}, "b_9": {"id": 25, "recipes": [["b_8", "base_5"]]}}}